shadowgate/__init__.py
shadowgate/_version.py
shadowgate/cli.py
shadowgate/client.py
shadowgate/engine.py
shadowgate/logging_setup.py
shadowgate/data/__init__.py
shadowgate/data/user_agents.json
shadowgate/data/wordslist.json
shadowgate/entities/__init__.py
shadowgate/entities/proxy.py
shadowgate/entities/result.py
shadowgate/utils/__init__.py
shadowgate/utils/misc.py
shadowgate/utils/proxy_helper.py
shadowgate/utils/useragent_helper.py
shadowgate/utils/wordlist_helper.py
shadowgate-0.1.1.dist-info/licenses/LICENSE
shadowgate-0.1.1.dist-info/METADATA
shadowgate-0.1.1.dist-info/WHEEL
shadowgate-0.1.1.dist-info/entry_points.txt
shadowgate-0.1.1.dist-info/top_level.txt
shadowgate-0.1.1.dist-info/RECORD
