Metadata-Version: 2.4
Name: shadowgate
Version: 0.1.1
Summary: Admin panel finder and directory brute-forcer (async HTTPX/Typer).
Author: Ali Moghimi
License: MIT
Project-URL: Homepage, https://github.com/yourusername/shadowgate
Project-URL: Repository, https://github.com/yourusername/shadowgate
Project-URL: Issues, https://github.com/yourusername/shadowgate/issues
Keywords: security,pentest,admin-finder,recon,httpx,cli
Classifier: Development Status :: 3 - Alpha
Classifier: Intended Audience :: Developers
Classifier: Intended Audience :: Information Technology
Classifier: Intended Audience :: System Administrators
Classifier: Topic :: Security
Classifier: Topic :: Internet :: WWW/HTTP
Classifier: Topic :: Software Development :: Testing
Classifier: Environment :: Console
Classifier: Programming Language :: Python :: 3
Classifier: Programming Language :: Python :: 3 :: Only
Classifier: Programming Language :: Python :: 3.10
Classifier: Programming Language :: Python :: 3.11
Classifier: Programming Language :: Python :: 3.12
Classifier: Programming Language :: Python :: 3.13
Classifier: License :: OSI Approved :: MIT License
Classifier: Operating System :: OS Independent
Requires-Python: >=3.10
License-File: LICENSE
Requires-Dist: httpx[http2,socks]>=0.27
Requires-Dist: tenacity>=8.4
Requires-Dist: typer>=0.12
Requires-Dist: rich>=13
Provides-Extra: dev
Requires-Dist: ruff>=0.6; extra == "dev"
Requires-Dist: pytest>=8; extra == "dev"
Requires-Dist: build>=1.2; extra == "dev"
Dynamic: license-file
